[
  { "row": 0, "col": 0, "ref": "esc", "x": 0, "y": 0, "w": 1, "h": 1 },
  { "row": 0, "col": 1, "ref": "# @", "x": 1.25, "y": 0, "w": 1, "h": 1 },
  { "row": 0, "col": 2, "ref": "1 &", "x": 2.25, "y": 0, "w": 1, "h": 1 },
  { "row": 0, "col": 3, "ref": "2 é", "x": 3.25, "y": 0, "w": 1, "h": 1 },
  { "row": 0, "col": 4, "ref": "3 \"", "x": 4.25, "y": 0, "w": 1, "h": 1 },
  { "row": 0, "col": 5, "ref": "4 '", "x": 5.25, "y": 0, "w": 1, "h": 1 },
  { "row": 0, "col": 6, "ref": "5 (", "x": 6.25, "y": 0, "w": 1, "h": 1 },
  { "row": 0, "col": 7, "ref": "6 §", "x": 7.25, "y": 0, "w": 1, "h": 1 },
  { "row": 0, "col": 8, "ref": "7 è", "x": 8.25, "y": 0, "w": 1, "h": 1 },
  { "row": 0, "col": 9, "ref": "8 !", "x": 9.25, "y": 0, "w": 1, "h": 1 },
  { "row": 0, "col": 10, "ref": "9 ç", "x": 10.25, "y": 0, "w": 1, "h": 1 },
  { "row": 0, "col": 11, "ref": "0 à", "x": 11.25, "y": 0, "w": 1, "h": 1 },
  { "row": 0, "col": 12, "ref": "° )", "x": 12.25, "y": 0, "w": 1, "h": 1 },
  { "row": 0, "col": 13, "ref": "_ -", "x": 13.25, "y": 0, "w": 1, "h": 1 },
  { "row": 0, "col": 14, "ref": "⌫", "x": 14.25, "y": 0, "w": 2, "h": 1 },
  { "row": 1, "col": 0, "ref": "", "x": 0, "y": 1, "w": 1, "h": 1 },
  { "row": 1, "col": 1, "ref": "⇥", "x": 1.25, "y": 1, "w": 1.5, "h": 1 },
  { "row": 1, "col": 2, "ref": "A", "x": 2.75, "y": 1, "w": 1, "h": 1 },
  { "row": 1, "col": 3, "ref": "Z", "x": 3.75, "y": 1, "w": 1, "h": 1 },
  { "row": 1, "col": 4, "ref": "E", "x": 4.75, "y": 1, "w": 1, "h": 1 },
  { "row": 1, "col": 5, "ref": "R", "x": 5.75, "y": 1, "w": 1, "h": 1 },
  { "row": 1, "col": 6, "ref": "T", "x": 6.75, "y": 1, "w": 1, "h": 1 },
  { "row": 1, "col": 7, "ref": "Y", "x": 7.75, "y": 1, "w": 1, "h": 1 },
  { "row": 1, "col": 8, "ref": "U", "x": 8.75, "y": 1, "w": 1, "h": 1 },
  { "row": 1, "col": 9, "ref": "I", "x": 9.75, "y": 1, "w": 1, "h": 1 },
  { "row": 1, "col": 10, "ref": "O", "x": 10.75, "y": 1, "w": 1, "h": 1 },
  { "row": 1, "col": 11, "ref": "P", "x": 11.75, "y": 1, "w": 1, "h": 1 },
  { "row": 1, "col": 12, "ref": "¨ ^", "x": 12.75, "y": 1, "w": 1, "h": 1 },
  { "row": 1, "col": 13, "ref": "* $", "x": 13.75, "y": 1, "w": 1, "h": 1 },
  {
    "row": 1,
    "col": 14,
    "ref": "",
    "x": 15,
    "y": 1,
    "w": 1.25,
    "h": 2,
    "secondRect": { "ref": "", "x": 14.75, "y": 2, "w": 1.25, "h": 1 }
  },
  { "row": 2, "col": 0, "ref": "", "x": 0, "y": 2, "w": 1, "h": 1 },
  { "row": 2, "col": 1, "ref": "⇪", "x": 1.25, "y": 2, "w": 1.75, "h": 1 },
  { "row": 2, "col": 2, "ref": "Q", "x": 3, "y": 2, "w": 1, "h": 1 },
  { "row": 2, "col": 3, "ref": "S", "x": 4, "y": 2, "w": 1, "h": 1 },
  { "row": 2, "col": 4, "ref": "D", "x": 5, "y": 2, "w": 1, "h": 1 },
  { "row": 2, "col": 5, "ref": "F", "x": 6, "y": 2, "w": 1, "h": 1 },
  { "row": 2, "col": 6, "ref": "G", "x": 7, "y": 2, "w": 1, "h": 1 },
  { "row": 2, "col": 7, "ref": "H", "x": 8, "y": 2, "w": 1, "h": 1 },
  { "row": 2, "col": 8, "ref": "J", "x": 9, "y": 2, "w": 1, "h": 1 },
  { "row": 2, "col": 9, "ref": "K", "x": 10, "y": 2, "w": 1, "h": 1 },
  { "row": 2, "col": 10, "ref": "L", "x": 11, "y": 2, "w": 1, "h": 1 },
  { "row": 2, "col": 11, "ref": "M", "x": 12, "y": 2, "w": 1, "h": 1 },
  { "row": 2, "col": 12, "ref": "% ù", "x": 13, "y": 2, "w": 1, "h": 1 },
  { "row": 2, "col": 13, "ref": "£ `", "x": 14, "y": 2, "w": 1, "h": 1 },
  { "row": 3, "col": 1, "ref": "⇧", "x": 1.25, "y": 3, "w": 1.25, "h": 1 },
  { "row": 3, "col": 2, "ref": "> <", "x": 2.5, "y": 3, "w": 1, "h": 1 },
  { "row": 3, "col": 3, "ref": "W", "x": 3.5, "y": 3, "w": 1, "h": 1 },
  { "row": 3, "col": 4, "ref": "X", "x": 4.5, "y": 3, "w": 1, "h": 1 },
  { "row": 3, "col": 5, "ref": "C", "x": 5.5, "y": 3, "w": 1, "h": 1 },
  { "row": 3, "col": 6, "ref": "V", "x": 6.5, "y": 3, "w": 1, "h": 1 },
  { "row": 3, "col": 7, "ref": "B", "x": 7.5, "y": 3, "w": 1, "h": 1 },
  { "row": 3, "col": 8, "ref": "N", "x": 8.5, "y": 3, "w": 1, "h": 1 },
  { "row": 3, "col": 9, "ref": "? ,", "x": 9.5, "y": 3, "w": 1, "h": 1 },
  { "row": 3, "col": 10, "ref": ". ;", "x": 10.5, "y": 3, "w": 1, "h": 1 },
  { "row": 3, "col": 11, "ref": "/ :", "x": 11.5, "y": 3, "w": 1, "h": 1 },
  { "row": 3, "col": 12, "ref": "+ =", "x": 12.5, "y": 3, "w": 1, "h": 1 },
  { "row": 3, "col": 13, "ref": "⇧", "x": 13.5, "y": 3, "w": 2.75, "h": 1 },
  { "row": 4, "col": 1, "ref": "⌃", "x": 1.25, "y": 4, "w": 1.75, "h": 1 },
  { "row": 4, "col": 2, "ref": "⌥", "x": 3, "y": 4, "w": 1.25, "h": 1 },
  { "row": 4, "col": 3, "ref": "⌘", "x": 4.25, "y": 4, "w": 1.25, "h": 1 },
  { "row": 4, "col": 5, "ref": "", "x": 5.5, "y": 4, "w": 2.25, "h": 1 },
  { "row": 4, "col": 7, "ref": "", "x": 7.75, "y": 4, "w": 2.75, "h": 1 },
  { "row": 4, "col": 9, "ref": "⌘", "x": 10.5, "y": 4, "w": 1.25, "h": 1 },
  { "row": 4, "col": 10, "ref": "⌥", "x": 11.75, "y": 4, "w": 1, "h": 1 },
  { "row": 4, "col": 12, "ref": "◀︎", "x": 13.25, "y": 4, "w": 1, "h": 1 },
  { "row": 4, "col": 13, "ref": "▼", "x": 14.25, "y": 4, "w": 1, "h": 1 },
  { "row": 4, "col": 14, "ref": "▶︎", "x": 15.25, "y": 4, "w": 1, "h": 1 }
]
